README.md
setup.py
classes/__init__.py
classes/address.py
classes/address_book.py
classes/birthday.py
classes/email.py
classes/field.py
classes/name.py
classes/note.py
classes/notes_book.py
classes/phone.py
classes/record.py
classes/tag.py
constants/__init__.py
constants/assistant_info.py
constants/auto_complete_cl.py
handlers/__init__.py
handlers/birthday_handlers.py
handlers/contacts_handlers.py
handlers/decorators.py
handlers/notes_handlers.py
handlers/parse_input.py
handlers/validations.py
helpers/__init__.py
helpers/assistant_info.py
helpers/autocomplete_config.py
helpers/logging_config.py
helpers/notes_pickle_utils.py
helpers/pickle_utils.py
helpers/startup_shutdown.py
project_S8cceS7f.egg-info/PKG-INFO
project_S8cceS7f.egg-info/SOURCES.txt
project_S8cceS7f.egg-info/dependency_links.txt
project_S8cceS7f.egg-info/entry_points.txt
project_S8cceS7f.egg-info/requires.txt
project_S8cceS7f.egg-info/top_level.txt